{"cameraMode":{"drawMode":0,"name":"Shaded","section":"Shading Mode"},"sceneLighting":true,"audioPlay":false,"sceneViewState":{"m_AlwaysRefresh":false,"showFog":true,"showSkybox":false,"showFlares":true,"showImageEffects":true,"showParticleSystems":true,"showVisualEffectGraphs":true,"m_FxEnabled":true},"in2DMode":false,"pivot":{"x":-2.0886998176574709,"y":3.330859661102295,"z":3.8745641708374025},"rotation":{"x":-0.12303858250379563,"y":0.7051712274551392,"z":-0.12639036774635316,"w":-0.6868165731430054},"size":9.577340126037598,"orthographic":false}