{"cameraMode":{"drawMode":0,"name":"Shaded","section":"Shading Mode"},"sceneLighting":true,"audioPlay":false,"sceneViewState":{"m_AlwaysRefresh":false,"showFog":true,"showSkybox":true,"showFlares":true,"showImageEffects":true,"showParticleSystems":true,"showVisualEffectGraphs":true,"m_FxEnabled":true},"in2DMode":false,"pivot":{"x":62.8999137878418,"y":140.34173583984376,"z":34.94300079345703},"rotation":{"x":-0.534606397151947,"y":-0.17807403206825257,"z":0.11836304515600205,"w":-0.8178479075431824},"size":47.19248962402344,"orthographic":false}